{"cameraMode":{"drawMode":0,"name":"Shaded","section":"Shading Mode"},"sceneLighting":true,"audioPlay":false,"sceneViewState":{"m_AlwaysRefresh":false,"showFog":true,"showSkybox":true,"showFlares":true,"showImageEffects":true,"showParticleSystems":true,"showVisualEffectGraphs":true,"m_FxEnabled":true},"in2DMode":false,"pivot":{"x":-48.58086013793945,"y":-0.5404338836669922,"z":-33.6115837097168},"rotation":{"x":0.04801047965884209,"y":0.7770331501960754,"z":-0.6250008940696716,"w":0.05944957584142685},"size":7.070122718811035,"orthographic":false}